AUTHORS.rst
HISTORY.rst
LICENSE
MANIFEST.in
README.rst
requirements.txt
setup.py
test_requirements.txt
gpsdshm/__init__.py
gpsdshm/shm.c
gpsdshm/shm.h
gpsdshm/shm.i
gpsdshm/shm.py
gpsdshm/shm_wrap.c
gpsdshm.egg-info/PKG-INFO
gpsdshm.egg-info/SOURCES.txt
gpsdshm.egg-info/dependency_links.txt
gpsdshm.egg-info/not-zip-safe
gpsdshm.egg-info/top_level.txt
tests/_mock.py
tests/test.nmea
tests/test_gpsdshm.py