Metadata-Version: 1.1
Name: gpsdshm
Version: 0.1.0
Summary: Python interface to gpsd shared memory
Home-page: https://github.com/mjuenema/python-gpsdshm
Author: Markus Juenemann
Author-email: markus@juenemann.net
License: BSD License
Keywords: gpsd,shared memory
Platform: UNKNOWN
Classifier: Development Status :: 4 - Beta
Classifier: Intended Audience :: Developers
Classifier: License :: OSI Approved :: BSD License
Classifier: Natural Language :: English
Classifier: Operating System :: Unix
Classifier: Topic :: Software Development :: Libraries
Classifier: Programming Language :: C
Classifier: Programming Language :: Python :: 2
Classifier: Programming Language :: Python :: 3
Classifier: Programming Language :: Python :: 2.6
Classifier: Programming Language :: Python :: 2.7
Classifier: Programming Language :: Python :: 3.3
Classifier: Programming Language :: Python :: 3.4
Classifier: Programming Language :: Python :: 3.5
